tidal/__init__.py
tidal/client.py
tidal/models/__init__.py
tidal/models/album.py
tidal/models/artist.py
tidal/models/base.py
tidal/models/media.py
tidal/models/metadata.py
tidal/models/resource.py
tidal/models/track.py
tidal/models/video.py
tidal/token_cache.py
tidal/types/__init__.py
tidal/types/token.py
tidal_ng-0.1.0.dist-info/METADATA
tidal_ng-0.1.0.dist-info/WHEEL
tidal_ng-0.1.0.dist-info/RECORD
