Metadata-Version: 2.1
Name: tidal-ng
Version: 0.1.0
Summary: Advanced API wrapper for Tidal music
Home-page: https://github.com/MrTransparentBox/tidal.py
License: MIT
Author: Alexander Johnson
Author-email: alexjohnson2004@gmail.com
Requires-Python: >=3.12,<4.0
Classifier: License :: OSI Approved :: MIT License
Classifier: Programming Language :: Python :: 3
Classifier: Programming Language :: Python :: 3.12
Requires-Dist: httpx[http2] (>=0.26.0,<0.27.0)
Project-URL: Repository, https://github.com/MrTransparentBox/tidal.py
